cloudshell/__init__.py
cloudshell/cp/__init__.py
cloudshell/cp/cloudstack/__init__.py
cloudshell/cp/cloudstack/constants.py
cloudshell/cp/cloudstack/exceptions.py
cloudshell/cp/cloudstack/actions/__init__.py
cloudshell/cp/cloudstack/actions/vm_details_actions.py
cloudshell/cp/cloudstack/api_client/__init__.py
cloudshell/cp/cloudstack/api_client/cloudstack_api.py
cloudshell/cp/cloudstack/entities/__init__.py
cloudshell/cp/cloudstack/entities/network.py
cloudshell/cp/cloudstack/entities/network_offering.py
cloudshell/cp/cloudstack/entities/network_type.py
cloudshell/cp/cloudstack/entities/vm.py
cloudshell/cp/cloudstack/flows/__init__.py
cloudshell/cp/cloudstack/flows/attributes_hint.py
cloudshell/cp/cloudstack/flows/connectivity.py
cloudshell/cp/cloudstack/flows/deploy.py
cloudshell/cp/cloudstack/flows/refresh_vm_ip.py
cloudshell/cp/cloudstack/flows/vm_details.py
cloudshell/cp/cloudstack/flows/vm_state.py
cloudshell/cp/cloudstack/helpers/__init__.py
cloudshell/cp/cloudstack/helpers/network_settings_helper.py
cloudshell/cp/cloudstack/helpers/threading.py
cloudshell/cp/cloudstack/models/DeployDataHolder.py
cloudshell/cp/cloudstack/models/__init__.py
cloudshell/cp/cloudstack/models/base_deployment_app.py
cloudshell/cp/cloudstack/models/connectivity_action_model.py
cloudshell/cp/cloudstack/models/deploy_app.py
cloudshell/cp/cloudstack/models/deployed_app.py
cloudshell/cp/cloudstack/models/resource_config.py
cloudshell/cp/cloudstack/services/__init__.py
cloudshell/cp/cloudstack/services/cloudstack_api_service.py
tests/__init__.py
tests/conftest.py
tests/cloudshell/__init__.py
tests/cloudshell/cp/__init__.py
tests/cloudshell/cp/cloudstack/__init__.py
tests/cloudshell/cp/cloudstack/models/__init__.py
tests/cloudshell/cp/cloudstack/models/test_resource_config.py
cloudshell_cp_cloudstack-1.0.0.dist-info/METADATA
cloudshell_cp_cloudstack-1.0.0.dist-info/WHEEL
cloudshell_cp_cloudstack-1.0.0.dist-info/top_level.txt
cloudshell_cp_cloudstack-1.0.0.dist-info/RECORD
