Metadata-Version: 2.1
Name: cloudshell-cp-cloudstack
Version: 1.0.0
Summary: <your package description>
Home-page: http://www.qualisystems.com/
Author: QualiSystems
Author-email: info@qualisystems.com
Requires-Python: ~=3.7
Requires-Dist: cloudshell-automation-api <2023.2,>=2022.1
Requires-Dist: attrs <23.2,>=22.0
Requires-Dist: cloudshell-shell-core ~=6.0
Requires-Dist: pydantic ~=2.4
Requires-Dist: retrying ~=1.3.3
Requires-Dist: requests <2.32,>=2.28
Requires-Dist: cloudshell-cp-core ~=2.5
Requires-Dist: cloudshell-logging ~=2.1
Requires-Dist: cloudshell-shell-connectivity-flow ~=4.2
Requires-Dist: cloudshell-shell-standards ~=2.0
Requires-Dist: jsonpickle ~=1.4
